{
    "projects": [
        {
            "title": "Face superposition normalization",
            "description": "Aplicação que normaliza um conjunto de fotos ao reposicioná-las em uma posição padrão de rosto fornecido. O objetivo desse projeto é facilitar a criação de vídeos time lapse que mostram a evolução ou a transição de rostos de pessoas.",
            "tools": ["Python", "OpenCV", "HaarCascade", "Processamento de Imagens"],
            "github_link": "https://github.com/diogohal/face-superposition-normalization"
        },
        {
            "title": "Mapa de intensidade com conta-gotas",
            "description": "Essa aplicação gera um mapa de intensidade com base nas distâncias Euclidiana e Mahalanobis em relação ao data frame obtido pelo conta-gotas usado na mesma imagem.",
            "tools": ["Python", "OpenCV", "Numpy", "Matplotlib", "Processamento de Imagens"],
            "github_link": "https://github.com/diogohal/intensity-map-similarity-measures"
        }
    ]
}